pytest_mproc/__init__.py
pytest_mproc/constants.py
pytest_mproc/coordinator.py
pytest_mproc/data.py
pytest_mproc/fixtures.py
pytest_mproc/http.py
pytest_mproc/main.py
pytest_mproc/orchestration.py
pytest_mproc/plugin.py
pytest_mproc/ptmproc_data.py
pytest_mproc/remote_sessions.py
pytest_mproc/user_output.py
pytest_mproc/utils.py
pytest_mproc/worker.py
pytest_mproc/remote/__init__.py
pytest_mproc/remote/bundle.py
pytest_mproc/remote/ssh.py
pytest_mproc-5.2.0.dist-info/LICENSE
pytest_mproc-5.2.0.dist-info/LICENSE.txt
pytest_mproc-5.2.0.dist-info/METADATA
pytest_mproc-5.2.0.dist-info/NOTICE
pytest_mproc-5.2.0.dist-info/WHEEL
pytest_mproc-5.2.0.dist-info/entry_points.txt
pytest_mproc-5.2.0.dist-info/top_level.txt
pytest_mproc-5.2.0.dist-info/RECORD
