Metadata-Version: 2.1
Name: pytest-mproc
Version: 5.2.0
Summary: low-startup-overhead, scalable, distributed-testing pytest plugin
Home-page: https://github.com/nak/pytest_mproc
Author: John Rusnak
Author-email: jrusnak69@gmail.com
License: BSD 2-CLAUSE
Download-URL: https://github.com/nak/pytest_mproc/dist/5.2.0
Keywords: pytest distributed multiprocessing
Platform: UNKNOWN
Classifier: Framework :: Pytest
Classifier: Development Status :: 4 - Beta
Classifier: License :: OSI Approved :: BSD License
Requires-Dist: aiocontext (>=0.1)
Requires-Dist: aiofile (>=3.7)
Requires-Dist: aiohttp (>=3.8)
Requires-Dist: pytest (>=6)
Requires-Dist: requests (>=2.27)
